{"cameraMode":{"drawMode":0,"name":"Shaded","section":"Shading Mode"},"sceneLighting":true,"audioPlay":false,"sceneViewState":{"m_AlwaysRefresh":false,"showFog":true,"showSkybox":true,"showFlares":true,"showImageEffects":true,"showParticleSystems":true,"showVisualEffectGraphs":true,"m_FxEnabled":true},"in2DMode":false,"pivot":{"x":-8.760002136230469,"y":4.190000057220459,"z":-2.2633609771728517},"rotation":{"x":-0.24749912321567536,"y":-0.74407559633255,"z":0.369445264339447,"w":-0.4986615777015686},"size":83.43038177490235,"orthographic":false}